{
  "data": {
    "article": {},
    "attachments": {},
    "author_id": "1790275346899554304",
    "context_annotations": [
      {
        "domain": {
          "description": "Categories within Brand Verticals that narrow down the scope of Brands",
          "id": "46",
          "name": "Business Taxonomy"
        },
        "entity": {
          "description": "Brands, companies, advertisers and every non-person handle with the profit intent related to softwares, apps, communication equipments, hardwares",
          "id": "1557697333571112960",
          "name": "Technology Business"
        }
      },
      {
        "domain": {
          "description": "for individual and types of technology, e.g., food technology, 3D printing",
          "id": "165",
          "name": "Technology"
        },
        "entity": {
          "description": "Technology and computing",
          "id": "848920371311001600",
          "name": "Technology"
        }
      },
      {
        "domain": {
          "description": "for individual and types of technology, e.g., food technology, 3D printing",
          "id": "165",
          "name": "Technology"
        },
        "entity": {
          "id": "1148689566112477184",
          "name": "Wi-Fi"
        }
      }
    ],
    "conversation_id": "1979113348189876301",
    "created_at": "2025-10-17T09:12:47.000Z",
    "edit_controls": {
      "editable_until": "2025-10-17T10:12:47.000Z",
      "edits_remaining": 5,
      "is_edit_eligible": false
    },
    "edit_history_tweet_ids": [
      "1979113348189876301"
    ],
    "entities": {
      "mentions": [
        {
          "end": 17,
          "id": "1413151000567771146",
          "start": 3,
          "username": "Windy_Skyline"
        }
      ]
    },
    "geo": {},
    "id": "1979113348189876301",
    "lang": "zh",
    "note_tweet": {
      "entities": {}
    },
    "possibly_sensitive": false,
    "public_metrics": {
      "bookmark_count": 0,
      "impression_count": 0,
      "like_count": 0,
      "quote_count": 0,
      "reply_count": 0,
      "retweet_count": 3
    },
    "referenced_tweets": [
      {
        "id": "1978984842886025457",
        "type": "retweeted"
      }
    ],
    "reply_settings": "everyone",
    "text": "RT @Windy_Skyline: 说个事情，上个月我刚回国，天府机场国际转国内行李直挂也需要在一个等候室里面看屏幕确认行李没有被拦才能走。结果一下飞机我手机卡莫名其妙失效了，wifi也得收验证码才能用，我抱着侥幸心态试了一下等候室的自动贩卖机能不能刷脸支付，结果它真能，让我…"
  },
  "includes": {
    "tweets": [
      {
        "article": {},
        "attachments": {},
        "author_id": "1790275346899554304",
        "context_annotations": [
          {
            "domain": {
              "description": "Categories within Brand Verticals that narrow down the scope of Brands",
              "id": "46",
              "name": "Business Taxonomy"
            },
            "entity": {
              "description": "Brands, companies, advertisers and every non-person handle with the profit intent related to softwares, apps, communication equipments, hardwares",
              "id": "1557697333571112960",
              "name": "Technology Business"
            }
          },
          {
            "domain": {
              "description": "for individual and types of technology, e.g., food technology, 3D printing",
              "id": "165",
              "name": "Technology"
            },
            "entity": {
              "description": "Technology and computing",
              "id": "848920371311001600",
              "name": "Technology"
            }
          },
          {
            "domain": {
              "description": "for individual and types of technology, e.g., food technology, 3D printing",
              "id": "165",
              "name": "Technology"
            },
            "entity": {
              "id": "1148689566112477184",
              "name": "Wi-Fi"
            }
          }
        ],
        "conversation_id": "1979113348189876301",
        "created_at": "2025-10-17T09:12:47.000Z",
        "edit_controls": {
          "editable_until": "2025-10-17T10:12:47.000Z",
          "edits_remaining": 5,
          "is_edit_eligible": false
        },
        "edit_history_tweet_ids": [
          "1979113348189876301"
        ],
        "entities": {
          "mentions": [
            {
              "end": 17,
              "id": "1413151000567771146",
              "start": 3,
              "username": "Windy_Skyline"
            }
          ]
        },
        "geo": {},
        "id": "1979113348189876301",
        "lang": "zh",
        "note_tweet": {
          "entities": {}
        },
        "possibly_sensitive": false,
        "public_metrics": {
          "bookmark_count": 0,
          "impression_count": 0,
          "like_count": 0,
          "quote_count": 0,
          "reply_count": 0,
          "retweet_count": 3
        },
        "referenced_tweets": [
          {
            "id": "1978984842886025457",
            "type": "retweeted"
          }
        ],
        "reply_settings": "everyone",
        "text": "RT @Windy_Skyline: 说个事情，上个月我刚回国，天府机场国际转国内行李直挂也需要在一个等候室里面看屏幕确认行李没有被拦才能走。结果一下飞机我手机卡莫名其妙失效了，wifi也得收验证码才能用，我抱着侥幸心态试了一下等候室的自动贩卖机能不能刷脸支付，结果它真能，让我…"
      },
      {
        "article": {},
        "attachments": {},
        "author_id": "1413151000567771146",
        "context_annotations": [
          {
            "domain": {
              "description": "Categories within Brand Verticals that narrow down the scope of Brands",
              "id": "46",
              "name": "Business Taxonomy"
            },
            "entity": {
              "description": "Brands, companies, advertisers and every non-person handle with the profit intent related to softwares, apps, communication equipments, hardwares",
              "id": "1557697333571112960",
              "name": "Technology Business"
            }
          },
          {
            "domain": {
              "description": "for individual and types of technology, e.g., food technology, 3D printing",
              "id": "165",
              "name": "Technology"
            },
            "entity": {
              "description": "Technology and computing",
              "id": "848920371311001600",
              "name": "Technology"
            }
          },
          {
            "domain": {
              "description": "for individual and types of technology, e.g., food technology, 3D printing",
              "id": "165",
              "name": "Technology"
            },
            "entity": {
              "id": "1148689566112477184",
              "name": "Wi-Fi"
            }
          }
        ],
        "conversation_id": "1978984842886025457",
        "created_at": "2025-10-17T00:42:08.000Z",
        "edit_controls": {
          "editable_until": "2025-10-17T01:42:08.000Z",
          "edits_remaining": 5,
          "is_edit_eligible": true
        },
        "edit_history_tweet_ids": [
          "1978984842886025457"
        ],
        "entities": {
          "urls": [
            {
              "display_url": "x.com/wanna8964fly/s…",
              "end": 159,
              "expanded_url": "https://twitter.com/wanna8964fly/status/1978800108604109268",
              "start": 136,
              "url": "https://t.co/0zovcgvMyG"
            }
          ]
        },
        "geo": {},
        "id": "1978984842886025457",
        "lang": "zh",
        "note_tweet": {
          "entities": {},
          "text": "说个事情，上个月我刚回国，天府机场国际转国内行李直挂也需要在一个等候室里面看屏幕确认行李没有被拦才能走。结果一下飞机我手机卡莫名其妙失效了，wifi也得收验证码才能用，我抱着侥幸心态试了一下等候室的自动贩卖机能不能刷脸支付，结果它真能，让我确认手机号对不对就支付成功了。\n然而我这个号根本就没用过，以前的支付宝账号给弃用了，我两年没回国，这个号也没同意过开通刷脸支付（理论上也没有可能偶然点过），他都能识别出来我是谁还允许成功支付，\n这说明一个私人公司都能精准识别数十亿用户的脸，直接确定到个人，如果是公共交通系统搞出来的人脸识别那就更不敢想了。\n如果这个东西给你放厕所门口，直接就追着你打"
        },
        "possibly_sensitive": false,
        "public_metrics": {
          "bookmark_count": 0,
          "impression_count": 2994,
          "like_count": 14,
          "quote_count": 1,
          "reply_count": 0,
          "retweet_count": 3
        },
        "referenced_tweets": [
          {
            "id": "1978800108604109268",
            "type": "quoted"
          }
        ],
        "reply_settings": "everyone",
        "text": "说个事情，上个月我刚回国，天府机场国际转国内行李直挂也需要在一个等候室里面看屏幕确认行李没有被拦才能走。结果一下飞机我手机卡莫名其妙失效了，wifi也得收验证码才能用，我抱着侥幸心态试了一下等候室的自动贩卖机能不能刷脸支付，结果它真能，让我确认手机号对不对就支付成功了。 https://t.co/0zovcgvMyG"
      }
    ],
    "users": [
      {
        "created_at": "2024-05-14T06:58:07.000Z",
        "description": "赛博黄皮子。                                 我们做的都是你不敢做的，我们说的都是你不敢说的，我们想的都是你不敢想的。 我们都是睚眦必报的，我们出手都是要见血的 ////////////商务三陪。🚪89单次图包64 非顺直男酌情降价////////////// ! 现接受定制服务",
        "id": "1790275346899554304",
        "location": "The pathway of no return",
        "name": "asuka 🏳️‍⚧️🍥🏳️‍🌈🏴",
        "pinned_tweet_id": "1926955766629474549",
        "profile_image_url": "https://pbs.twimg.com/profile_images/1953772921652228097/ZqPFazZE_normal.jpg",
        "protected": false,
        "public_metrics": {
          "followers_count": 811,
          "following_count": 1258,
          "like_count": 7433,
          "listed_count": 2,
          "media_count": 515,
          "tweet_count": 4830
        },
        "username": "H4lf_L13_F8964",
        "verified": false
      },
      {
        "created_at": "2021-07-08T15:00:38.000Z",
        "description": "1、别来烦我 2、我中文不好，别来挑毛病 以后一部分日常推会放在这个号上面@J_AWindy 3、我不歧视顺直人 4、别来碰瓷 5、如果你不知道你为什么被我block了，那就是你们出现在了不该点赞的推文like/retweet列表里，即使你是我线下认识的人我也不会放你出来 6、侮女词别来我推文互动沾边",
        "entities": {
          "description": {
            "mentions": [
              {
                "end": 46,
                "start": 37,
                "username": "J_AWindy"
              }
            ]
          },
          "url": {
            "urls": [
              {
                "display_url": "blackdeath.club",
                "end": 23,
                "expanded_url": "http://blackdeath.club/",
                "start": 0,
                "url": "https://t.co/VcVji2Z02J"
              }
            ]
          }
        },
        "id": "1413151000567771146",
        "location": "6ft↓",
        "name": "👾",
        "pinned_tweet_id": "1602731469398573061",
        "profile_image_url": "https://pbs.twimg.com/profile_images/1928749874175995904/qJJj7FqI_normal.jpg",
        "protected": false,
        "public_metrics": {
          "followers_count": 1252,
          "following_count": 211,
          "like_count": 2306,
          "listed_count": 6,
          "media_count": 3205,
          "tweet_count": 11043
        },
        "url": "https://t.co/VcVji2Z02J",
        "username": "Windy_Skyline",
        "verified": true
      }
    ]
  }
}