{
  "data": {
    "article": {},
    "attachments": {
      "media_keys": [
        "3_2004081981366079489",
        "3_2004081981357699072",
        "3_2004081981353562112",
        "3_2004081981361913856"
      ]
    },
    "author_id": "1790275346899554304",
    "conversation_id": "2004081989495017753",
    "created_at": "2025-12-25T06:49:14.000Z",
    "edit_controls": {
      "editable_until": "2025-12-25T07:49:14.000Z",
      "edits_remaining": 5,
      "is_edit_eligible": true
    },
    "edit_history_tweet_ids": [
      "2004081989495017753"
    ],
    "entities": {
      "urls": [
        {
          "display_url": "pic.x.com/dHwDVr4HVV",
          "end": 44,
          "expanded_url": "https://x.com/H4lf_L13_F8964/status/2004081989495017753/photo/1",
          "media_key": "3_2004081981366079489",
          "start": 21,
          "url": "https://t.co/dHwDVr4HVV"
        },
        {
          "display_url": "pic.x.com/dHwDVr4HVV",
          "end": 44,
          "expanded_url": "https://x.com/H4lf_L13_F8964/status/2004081989495017753/photo/1",
          "media_key": "3_2004081981357699072",
          "start": 21,
          "url": "https://t.co/dHwDVr4HVV"
        },
        {
          "display_url": "pic.x.com/dHwDVr4HVV",
          "end": 44,
          "expanded_url": "https://x.com/H4lf_L13_F8964/status/2004081989495017753/photo/1",
          "media_key": "3_2004081981353562112",
          "start": 21,
          "url": "https://t.co/dHwDVr4HVV"
        },
        {
          "display_url": "pic.x.com/dHwDVr4HVV",
          "end": 44,
          "expanded_url": "https://x.com/H4lf_L13_F8964/status/2004081989495017753/photo/1",
          "media_key": "3_2004081981361913856",
          "start": 21,
          "url": "https://t.co/dHwDVr4HVV"
        }
      ]
    },
    "geo": {},
    "id": "2004081989495017753",
    "lang": "zh",
    "note_tweet": {
      "entities": {}
    },
    "possibly_sensitive": false,
    "public_metrics": {
      "bookmark_count": 0,
      "impression_count": 0,
      "like_count": 0,
      "quote_count": 0,
      "reply_count": 0,
      "retweet_count": 0
    },
    "reply_settings": "everyone",
    "text": "上野千鹤子也是terf\n一边否认一边隐身 https://t.co/dHwDVr4HVV"
  },
  "includes": {
    "media": [
      {
        "height": 1426,
        "media_key": "3_2004081981366079489",
        "public_metrics": {},
        "type": "photo",
        "url": "https://pbs.twimg.com/media/G8_t8agWEAEuqdL.jpg",
        "width": 1170
      },
      {
        "height": 2048,
        "media_key": "3_2004081981357699072",
        "public_metrics": {},
        "type": "photo",
        "url": "https://pbs.twimg.com/media/G8_t8aeWMAAOAk9.jpg",
        "width": 1970
      },
      {
        "height": 2048,
        "media_key": "3_2004081981353562112",
        "public_metrics": {},
        "type": "photo",
        "url": "https://pbs.twimg.com/media/G8_t8adXEAAHXjm.jpg",
        "width": 1746
      },
      {
        "height": 2048,
        "media_key": "3_2004081981361913856",
        "public_metrics": {},
        "type": "photo",
        "url": "https://pbs.twimg.com/media/G8_t8afWgAA1_3O.jpg",
        "width": 1840
      }
    ],
    "tweets": [
      {
        "article": {},
        "attachments": {
          "media_keys": [
            "3_2004081981366079489",
            "3_2004081981357699072",
            "3_2004081981353562112",
            "3_2004081981361913856"
          ]
        },
        "author_id": "1790275346899554304",
        "conversation_id": "2004081989495017753",
        "created_at": "2025-12-25T06:49:14.000Z",
        "edit_controls": {
          "editable_until": "2025-12-25T07:49:14.000Z",
          "edits_remaining": 5,
          "is_edit_eligible": true
        },
        "edit_history_tweet_ids": [
          "2004081989495017753"
        ],
        "entities": {
          "urls": [
            {
              "display_url": "pic.x.com/dHwDVr4HVV",
              "end": 44,
              "expanded_url": "https://x.com/H4lf_L13_F8964/status/2004081989495017753/photo/1",
              "media_key": "3_2004081981366079489",
              "start": 21,
              "url": "https://t.co/dHwDVr4HVV"
            },
            {
              "display_url": "pic.x.com/dHwDVr4HVV",
              "end": 44,
              "expanded_url": "https://x.com/H4lf_L13_F8964/status/2004081989495017753/photo/1",
              "media_key": "3_2004081981357699072",
              "start": 21,
              "url": "https://t.co/dHwDVr4HVV"
            },
            {
              "display_url": "pic.x.com/dHwDVr4HVV",
              "end": 44,
              "expanded_url": "https://x.com/H4lf_L13_F8964/status/2004081989495017753/photo/1",
              "media_key": "3_2004081981353562112",
              "start": 21,
              "url": "https://t.co/dHwDVr4HVV"
            },
            {
              "display_url": "pic.x.com/dHwDVr4HVV",
              "end": 44,
              "expanded_url": "https://x.com/H4lf_L13_F8964/status/2004081989495017753/photo/1",
              "media_key": "3_2004081981361913856",
              "start": 21,
              "url": "https://t.co/dHwDVr4HVV"
            }
          ]
        },
        "geo": {},
        "id": "2004081989495017753",
        "lang": "zh",
        "note_tweet": {
          "entities": {}
        },
        "possibly_sensitive": false,
        "public_metrics": {
          "bookmark_count": 0,
          "impression_count": 0,
          "like_count": 0,
          "quote_count": 0,
          "reply_count": 0,
          "retweet_count": 0
        },
        "reply_settings": "everyone",
        "text": "上野千鹤子也是terf\n一边否认一边隐身 https://t.co/dHwDVr4HVV"
      }
    ],
    "users": [
      {
        "created_at": "2024-05-14T06:58:07.000Z",
        "description": "赛博黄皮子。                                 我们做的都是你不敢做的，我们说的都是你不敢说的，我们想的都是你不敢想的。 我们都是睚眦必报的，我们出手都是要见血的 ////////////商务三陪。🚪89单次图包64 非顺直男酌情降价////////////// ! 现接受定制服务",
        "id": "1790275346899554304",
        "location": "The pathway of no return",
        "name": "asuka 🏳️‍⚧️🍥🏳️‍🌈🏴",
        "pinned_tweet_id": "1926955766629474549",
        "profile_image_url": "https://pbs.twimg.com/profile_images/1953772921652228097/ZqPFazZE_normal.jpg",
        "protected": false,
        "public_metrics": {
          "followers_count": 828,
          "following_count": 1315,
          "like_count": 8116,
          "listed_count": 2,
          "media_count": 541,
          "tweet_count": 5129
        },
        "username": "H4lf_L13_F8964",
        "verified": false
      }
    ]
  }
}