{
  "data": {
    "article": {},
    "attachments": {},
    "author_id": "1790275346899554304",
    "conversation_id": "1936276814206492862",
    "created_at": "2025-06-21T07:55:02.000Z",
    "edit_controls": {
      "editable_until": "2025-06-21T08:55:02.000Z",
      "edits_remaining": 5,
      "is_edit_eligible": false
    },
    "edit_history_tweet_ids": [
      "1936332017748394026"
    ],
    "entities": {
      "mentions": [
        {
          "end": 8,
          "id": "1601496535375949824",
          "start": 0,
          "username": "yzhlzi3"
        }
      ]
    },
    "geo": {},
    "id": "1936332017748394026",
    "in_reply_to_user_id": "1601496535375949824",
    "lang": "zh",
    "note_tweet": {
      "entities": {}
    },
    "possibly_sensitive": false,
    "public_metrics": {
      "bookmark_count": 0,
      "impression_count": 0,
      "like_count": 0,
      "quote_count": 0,
      "reply_count": 0,
      "retweet_count": 0
    },
    "referenced_tweets": [
      {
        "id": "1936276814206492862",
        "type": "replied_to"
      }
    ],
    "reply_settings": "everyone",
    "text": "@yzhlzi3 必然要革了山川河流，江河湖海，天体 宇宙乃至 各宏观微观粒子的命。把万物打倒在地，踏上一只脚，让它们永世不得翻身。只要向着极限进军就是无极。"
  },
  "includes": {
    "media": [
      {
        "height": 1393,
        "media_key": "3_1936276811580596224",
        "public_metrics": {},
        "type": "photo",
        "url": "https://pbs.twimg.com/media/Gt8JgFUWYAAl7qN.jpg",
        "width": 1080
      }
    ],
    "tweets": [
      {
        "article": {},
        "attachments": {},
        "author_id": "1790275346899554304",
        "conversation_id": "1936276814206492862",
        "created_at": "2025-06-21T07:55:02.000Z",
        "edit_controls": {
          "editable_until": "2025-06-21T08:55:02.000Z",
          "edits_remaining": 5,
          "is_edit_eligible": false
        },
        "edit_history_tweet_ids": [
          "1936332017748394026"
        ],
        "entities": {
          "mentions": [
            {
              "end": 8,
              "id": "1601496535375949824",
              "start": 0,
              "username": "yzhlzi3"
            }
          ]
        },
        "geo": {},
        "id": "1936332017748394026",
        "in_reply_to_user_id": "1601496535375949824",
        "lang": "zh",
        "note_tweet": {
          "entities": {}
        },
        "possibly_sensitive": false,
        "public_metrics": {
          "bookmark_count": 0,
          "impression_count": 0,
          "like_count": 0,
          "quote_count": 0,
          "reply_count": 0,
          "retweet_count": 0
        },
        "referenced_tweets": [
          {
            "id": "1936276814206492862",
            "type": "replied_to"
          }
        ],
        "reply_settings": "everyone",
        "text": "@yzhlzi3 必然要革了山川河流，江河湖海，天体 宇宙乃至 各宏观微观粒子的命。把万物打倒在地，踏上一只脚，让它们永世不得翻身。只要向着极限进军就是无极。"
      },
      {
        "article": {},
        "attachments": {
          "media_keys": [
            "3_1936276811580596224"
          ]
        },
        "author_id": "1601496535375949824",
        "conversation_id": "1936276814206492862",
        "created_at": "2025-06-21T04:15:41.000Z",
        "edit_controls": {
          "editable_until": "2025-06-21T05:15:41.000Z",
          "edits_remaining": 5,
          "is_edit_eligible": true
        },
        "edit_history_tweet_ids": [
          "1936276814206492862"
        ],
        "entities": {
          "urls": [
            {
              "display_url": "pic.x.com/hvG1kd0iez",
              "end": 33,
              "expanded_url": "https://x.com/yzhlzi3/status/1936276814206492862/photo/1",
              "media_key": "3_1936276811580596224",
              "start": 10,
              "url": "https://t.co/hvG1kd0iez"
            }
          ]
        },
        "geo": {},
        "id": "1936276814206492862",
        "lang": "zh",
        "note_tweet": {
          "entities": {}
        },
        "possibly_sensitive": false,
        "public_metrics": {
          "bookmark_count": 7,
          "impression_count": 9679,
          "like_count": 232,
          "quote_count": 1,
          "reply_count": 22,
          "retweet_count": 11
        },
        "reply_settings": "everyone",
        "text": "我超级喜欢这个照片 https://t.co/hvG1kd0iez"
      }
    ],
    "users": [
      {
        "created_at": "2024-05-14T06:58:07.000Z",
        "description": "我们做的都是你不敢做的，我们说的都是你不敢说的，我们想的都是你不敢想的。 我们都是睚眦必报的，我们出手都是要见血的 ////////////商务三陪。🚪89单次图包64 非顺直男酌情降价////////////// ! 现接受定制服务",
        "id": "1790275346899554304",
        "location": "The pathway of no return",
        "name": "asuka 🏳️‍⚧️🍥🏳️‍🌈🏴",
        "pinned_tweet_id": "1926955766629474549",
        "profile_image_url": "https://pbs.twimg.com/profile_images/1915506274004828160/c99MGKyD_normal.jpg",
        "protected": false,
        "public_metrics": {
          "followers_count": 663,
          "following_count": 1074,
          "like_count": 5844,
          "listed_count": 0,
          "media_count": 410,
          "tweet_count": 4052
        },
        "username": "H4lf_L13_F8964",
        "verified": false
      },
      {
        "created_at": "2022-12-10T08:38:33.000Z",
        "description": "这个世界已经没救了，但是，是你的话就可以改变命运！无法回避的毁灭与叹息，把他们全部颠覆就好啦。你也具备这样的力量！所以与我签订契约    成为魔法少女吧！☆梗图G7人，时常鬼上身。",
        "entities": {
          "url": {
            "urls": [
              {
                "display_url": "b23.tv/ep63470",
                "end": 23,
                "expanded_url": "https://b23.tv/ep63470",
                "start": 0,
                "url": "https://t.co/eT65Fp4Uh5"
              }
            ]
          }
        },
        "id": "1601496535375949824",
        "location": "云梦泽",
        "name": "一只̶狸̶子̶🍜",
        "pinned_tweet_id": "1758014861924319355",
        "profile_image_url": "https://pbs.twimg.com/profile_images/1907292253963624448/kRhiIHLg_normal.jpg",
        "protected": false,
        "public_metrics": {
          "followers_count": 3256,
          "following_count": 846,
          "like_count": 45598,
          "listed_count": 20,
          "media_count": 2974,
          "tweet_count": 13354
        },
        "url": "https://t.co/eT65Fp4Uh5",
        "username": "yzhlzi3",
        "verified": false
      }
    ]
  }
}